{
    "errors": [],
    "data": [
        {
            "id": "{{ id }}",
            "id_v1": "/lights/{{ id }}",
            "type": "device",
            "metadata": {
                "name": "{{ name }}",
                "archetype": "window_covering_device"
            },
            "services": [
                {
                    "rid": "{{ light_service_id }}",
                    "rtype": "light"
                }
            ],
            "product_data": {
                "model_id": "WC001",
                "manufacturer_name": "Philips",
                "product_name": "Smart blinds",
                "product_archetype": "window_covering_device",
                "certified": true,
                "software_version": "1.88.1",
                "hardware_platform_type": "100b-103"
            }
        }
    ]
}
